{"sid": "pboqng", "link": "/r/CollegeRant/comments/pboqng/student_regrets_being_unmuted_during_lecture/", "title:": "Student Regrets Being Unmuted During Lecture", "text": "This happened in my lecture.  Dude didn't realize that he was muted.\n\n&#x200B;\n\n[Leave a like on youtube: https:\\/\\/youtu.be\\/RQKFAJWnkJo](https://reddit.com/link/pboqng/video/6mn9r1wxolj71/player)", "author": "PrivateMTD", "created": 1629939406, "retrieved": 1632841559, "over_18": false, "upvotes": 10, "upvote_ratio": 0.92, "comments": {"had7cdo": {"link": "/r/CollegeRant/comments/pboqng/student_regrets_being_unmuted_during_lecture/had7cdo/", "text": "Thank you u/PrivateMTD for posting on r/collegerant. \n\nRemember to read the rules and report rule breaking posts.\n\n\n*I am a bot, and this action was performed automatically. Please [contact the moderators of this subreddit](/message/compose/?to=/r/CollegeRant) if you have any questions or concerns.*", "author": "AutoModerator", "created": 1629939532, "upvotes": 1}, "hadzdtq": {"link": "/r/CollegeRant/comments/pboqng/student_regrets_being_unmuted_during_lecture/hadzdtq/", "text": "Why they kick bro out \ud83d\ude10", "author": "Independent_Bad_9904", "created": 1629953673, "upvotes": 2}, "hadsx6r": {"link": "/r/CollegeRant/comments/pboqng/student_regrets_being_unmuted_during_lecture/hadsx6r/", "text": "so embarassing", "author": "matsudasociety", "created": 1629949868, "upvotes": 3}}}