{
  "sid": "nolbfy",
  "link": "/r/college/comments/nolbfy/graduation/",
  "title:": "Graduation.",
  "text": "Ladies and gentlemen, I have made it, today I submitted my last final exam and earned my Bachelor's.",
  "author": "HamedR6S",
  "created": 1622410880,
  "over_18": false,
  "upvotes": 708,
  "upvote_ratio": 0.99,
  "comments": {
    "h05ayy2": {
      "link": "/r/college/comments/nolbfy/graduation/h05ayy2/",
      "text": "I am 3 assignments away",
      "author": "Impressive-Name5129",
      "created": 1622512549,
      "upvotes": 2,
      "replies": {
        "h08ofea": {
          "link": "/r/college/comments/nolbfy/graduation/h08ofea/",
          "text": "You are soon going to finish!",
          "author": "HamedR6S",
          "created": 1622583299,
          "upvotes": 1,
          "replies": {}
        }
      }
    },
    "h04sal0": {
      "link": "/r/college/comments/nolbfy/graduation/h04sal0/",
      "text": "Congratulations \ud83c\udf89 proud of you!!!",
      "author": "ColBoundDTermination",
      "created": 1622502485,
      "upvotes": 2,
      "replies": {
        "h08ody0": {
          "link": "/r/college/comments/nolbfy/graduation/h08ody0/",
          "text": "Omg thank you!!",
          "author": "HamedR6S",
          "created": 1622583280,
          "upvotes": 1,
          "replies": {}
        }
      }
    },
    "h040r6r": {
      "link": "/r/college/comments/nolbfy/graduation/h040r6r/",
      "text": "Congrats!",
      "author": "sushimonster13",
      "created": 1622488196,
      "upvotes": 2,
      "replies": {
        "h04qjmq": {
          "link": "/r/college/comments/nolbfy/graduation/h04qjmq/",
          "text": "Thank you Mr sushi monster",
          "author": "HamedR6S",
          "created": 1622501504,
          "upvotes": 2,
          "replies": {}
        }
      }
    },
    "h03tsv4": {
      "link": "/r/college/comments/nolbfy/graduation/h03tsv4/",
      "text": "Nice and Congrats! I just graduated as well 2 weeks ago. Best feeling in the world!   \nReward yourself binge watching shows you've missed over the years and a nice long nap because that's what I did.",
      "author": "Espada-Facade",
      "created": 1622484758,
      "upvotes": 2,
      "replies": {
        "h04qinn": {
          "link": "/r/college/comments/nolbfy/graduation/h04qinn/",
          "text": "Many thanks mate!\nI have a few old shows I wanna rewatch and I need to catch up on some YouTube content.",
          "author": "HamedR6S",
          "created": 1622501489,
          "upvotes": 1,
          "replies": {}
        }
      }
    },
    "h03ma61": {
      "link": "/r/college/comments/nolbfy/graduation/h03ma61/",
      "text": "this post made me so happy as if i'm the one graduating lmao CONGRATSSS",
      "author": "Some_Random-Name01",
      "created": 1622481094,
      "upvotes": 2,
      "replies": {
        "h04qey5": {
          "link": "/r/college/comments/nolbfy/graduation/h04qey5/",
          "text": "Hahahaha I'm happy it did. I cannot believe that I'm done! Thank youu",
          "author": "HamedR6S",
          "created": 1622501434,
          "upvotes": 1,
          "replies": {}
        }
      }
    },
    "h03klko": {
      "link": "/r/college/comments/nolbfy/graduation/h03klko/",
      "text": "Congratulations!!!",
      "author": "dani0218",
      "created": 1622480270,
      "upvotes": 2,
      "replies": {}
    },
    "h03dsy0": {
      "link": "/r/college/comments/nolbfy/graduation/h03dsy0/",
      "text": "I got min in 1982, welcome.",
      "author": "doubt__first",
      "created": 1622476932,
      "upvotes": -2,
      "replies": {
        "h047szg": {
          "link": "/r/college/comments/nolbfy/graduation/h047szg/",
          "text": "You a old mother fucker",
          "author": "invincible-upper-boy",
          "created": 1622491732,
          "upvotes": 2,
          "replies": {}
        },
        "h04qurc": {
          "link": "/r/college/comments/nolbfy/graduation/h04qurc/",
          "text": "Tad bit late, but congrats",
          "author": "HamedR6S",
          "created": 1622501678,
          "upvotes": 1,
          "replies": {}
        }
      }
    },
    "h03bztl": {
      "link": "/r/college/comments/nolbfy/graduation/h03bztl/",
      "text": "Congratulations!",
      "author": "Excellent-Letter-780",
      "created": 1622476046,
      "upvotes": 2,
      "replies": {
        "h04qvet": {
          "link": "/r/college/comments/nolbfy/graduation/h04qvet/",
          "text": "Thank you",
          "author": "HamedR6S",
          "created": 1622501688,
          "upvotes": 1,
          "replies": {}
        }
      }
    },
    "h0365dk": {
      "link": "/r/college/comments/nolbfy/graduation/h0365dk/",
      "text": "That\u2019s the dream! Good job!",
      "author": "Nevertrumper2019",
      "created": 1622473104,
      "upvotes": 2,
      "replies": {
        "h036rq3": {
          "link": "/r/college/comments/nolbfy/graduation/h036rq3/",
          "text": "You're the dream \ud83d\ude09, thanks!",
          "author": "HamedR6S",
          "created": 1622473415,
          "upvotes": 2,
          "replies": {}
        }
      }
    },
    "h02uvre": {
      "link": "/r/college/comments/nolbfy/graduation/h02uvre/",
      "text": "What are you graduating in?",
      "author": "invincible-upper-boy",
      "created": 1622466961,
      "upvotes": 3,
      "replies": {
        "h036nsv": {
          "link": "/r/college/comments/nolbfy/graduation/h036nsv/",
          "text": "Major in management information systems, minor in data analytics and digital security",
          "author": "HamedR6S",
          "created": 1622473360,
          "upvotes": 2,
          "replies": {}
        }
      }
    },
    "h02uh5v": {
      "link": "/r/college/comments/nolbfy/graduation/h02uh5v/",
      "text": "Proud of you son",
      "author": "Comprehensive_Face32",
      "created": 1622466711,
      "upvotes": 2,
      "replies": {
        "h036eq4": {
          "link": "/r/college/comments/nolbfy/graduation/h036eq4/",
          "text": "Thanks yo!",
          "author": "HamedR6S",
          "created": 1622473233,
          "upvotes": 1,
          "replies": {}
        }
      }
    },
    "h02ohfb": {
      "link": "/r/college/comments/nolbfy/graduation/h02ohfb/",
      "text": "congratulations!  all your hard work payed off :)",
      "author": "buckaroo3030",
      "created": 1622462683,
      "upvotes": 3,
      "replies": {
        "h02s6lc": {
          "link": "/r/college/comments/nolbfy/graduation/h02s6lc/",
          "text": "Honestly, I'm glad it did",
          "author": "HamedR6S",
          "created": 1622465257,
          "upvotes": 2,
          "replies": {}
        }
      }
    },
    "h02ln8m": {
      "link": "/r/college/comments/nolbfy/graduation/h02ln8m/",
      "text": "Congratulations.",
      "author": "ArmadilloReasonable7",
      "created": 1622460443,
      "upvotes": 3,
      "replies": {
        "h02lpfb": {
          "link": "/r/college/comments/nolbfy/graduation/h02lpfb/",
          "text": "Thank you.",
          "author": "HamedR6S",
          "created": 1622460493,
          "upvotes": 3,
          "replies": {}
        }
      }
    },
    "h02kr8r": {
      "link": "/r/college/comments/nolbfy/graduation/h02kr8r/",
      "text": "Nice!!!! Can I ask what your area of study was?",
      "author": "Georgeclintorus",
      "created": 1622459697,
      "upvotes": 6,
      "replies": {
        "h02kux3": {
          "link": "/r/college/comments/nolbfy/graduation/h02kux3/",
          "text": "Absolutely!\nI majored in Management information system, with a minor in data analytics and digital security.",
          "author": "HamedR6S",
          "created": 1622459784,
          "upvotes": 11,
          "replies": {
            "h02rq3u": {
              "link": "/r/college/comments/nolbfy/graduation/h02rq3u/",
              "text": "Very high in demand, that's terrific.",
              "author": "acm2033",
              "created": 1622464954,
              "upvotes": 10,
              "replies": {}
            }
          }
        }
      }
    },
    "h02iluu": {
      "link": "/r/college/comments/nolbfy/graduation/h02iluu/",
      "text": "CONGRATS",
      "author": "en-chica",
      "created": 1622457791,
      "upvotes": 3,
      "replies": {
        "h02lp68": {
          "link": "/r/college/comments/nolbfy/graduation/h02lp68/",
          "text": "THANKS",
          "author": "HamedR6S",
          "created": 1622460487,
          "upvotes": 2,
          "replies": {}
        }
      }
    },
    "h02400r": {
      "link": "/r/college/comments/nolbfy/graduation/h02400r/",
      "text": "CONGRATULATIONS!!!!! IM SO PROUD OF YOUUUU ALL THE ACADEMIC REQUIREMENTS ARE FINALLY DONE!!!! DONT FORGET TO REWARD YO SELF!!!",
      "author": null,
      "created": 1622444014,
      "upvotes": 10,
      "replies": {
        "h02cs7f": {
          "link": "/r/college/comments/nolbfy/graduation/h02cs7f/",
          "text": "THANK YOUUUU! I'm going away to relax for a week straight!",
          "author": "HamedR6S",
          "created": 1622452153,
          "upvotes": 6,
          "replies": {}
        }
      }
    },
    "h01vkl8": {
      "link": "/r/college/comments/nolbfy/graduation/h01vkl8/",
      "text": "Welcome to lots of debt and struggling to find a job. \ud83d\ude0a",
      "author": "SuperiorT",
      "created": 1622437466,
      "upvotes": 2,
      "replies": {
        "h0226t7": {
          "link": "/r/college/comments/nolbfy/graduation/h0226t7/",
          "text": "Depends on your major",
          "author": "best_casual_mma_",
          "created": 1622442526,
          "upvotes": 3,
          "replies": {
            "h022de9": {
              "link": "/r/college/comments/nolbfy/graduation/h022de9/",
              "text": "I guess",
              "author": "SuperiorT",
              "created": 1622442676,
              "upvotes": 1,
              "replies": {}
            }
          }
        },
        "h02cpu8": {
          "link": "/r/college/comments/nolbfy/graduation/h02cpu8/",
          "text": "That sounds welcoming :(",
          "author": "HamedR6S",
          "created": 1622452086,
          "upvotes": 2,
          "replies": {
            "h02tydv": {
              "link": "/r/college/comments/nolbfy/graduation/h02tydv/",
              "text": "\"Reality Is Often Disappointing\" - Thanos",
              "author": "SuperiorT",
              "created": 1622466384,
              "upvotes": 3,
              "replies": {}
            }
          }
        }
      }
    },
    "h01un9h": {
      "link": "/r/college/comments/nolbfy/graduation/h01un9h/",
      "text": "Congratulations \ud83c\udf8a",
      "author": "the_alt_curlyfries",
      "created": 1622436808,
      "upvotes": 3,
      "replies": {
        "h02cstp": {
          "link": "/r/college/comments/nolbfy/graduation/h02cstp/",
          "text": "Many thankss!",
          "author": "HamedR6S",
          "created": 1622452170,
          "upvotes": 3,
          "replies": {}
        }
      }
    },
    "h01rhrr": {
      "link": "/r/college/comments/nolbfy/graduation/h01rhrr/",
      "text": "Congratulations!! \ud83c\udf89",
      "author": "prirah",
      "created": 1622434642,
      "upvotes": 3,
      "replies": {
        "h02cskd": {
          "link": "/r/college/comments/nolbfy/graduation/h02cskd/",
          "text": "Thankss!!",
          "author": "HamedR6S",
          "created": 1622452163,
          "upvotes": 3,
          "replies": {}
        }
      }
    },
    "h01oqo1": {
      "link": "/r/college/comments/nolbfy/graduation/h01oqo1/",
      "text": "[removed]",
      "author": null,
      "created": 1622432822,
      "upvotes": 1,
      "replies": {}
    },
    "h017zy1": {
      "link": "/r/college/comments/nolbfy/graduation/h017zy1/",
      "text": "Yay!",
      "author": "QueenZeon101",
      "created": 1622422946,
      "upvotes": 3,
      "replies": {}
    },
    "h010ep1": {
      "link": "/r/college/comments/nolbfy/graduation/h010ep1/",
      "text": "Congrats!!",
      "author": "yehawyipyip",
      "created": 1622418605,
      "upvotes": 8,
      "replies": {
        "h02coux": {
          "link": "/r/college/comments/nolbfy/graduation/h02coux/",
          "text": "Thanks!!",
          "author": "HamedR6S",
          "created": 1622452059,
          "upvotes": 3,
          "replies": {}
        }
      }
    },
    "h00yc2e": {
      "link": "/r/college/comments/nolbfy/graduation/h00yc2e/",
      "text": "You sumbitch Congrats!! *slaps keister firmly*",
      "author": "airbear13",
      "created": 1622417434,
      "upvotes": 14,
      "replies": {
        "h02cnw9": {
          "link": "/r/college/comments/nolbfy/graduation/h02cnw9/",
          "text": "Hahahaha yaaasss, we are donee",
          "author": "HamedR6S",
          "created": 1622452034,
          "upvotes": 6,
          "replies": {}
        }
      }
    },
    "h00v81m": {
      "link": "/r/college/comments/nolbfy/graduation/h00v81m/",
      "text": "Congrats!!!!",
      "author": "Crochitting",
      "created": 1622415692,
      "upvotes": 9,
      "replies": {
        "h02cmrr": {
          "link": "/r/college/comments/nolbfy/graduation/h02cmrr/",
          "text": "Thanks buddyy",
          "author": "HamedR6S",
          "created": 1622452002,
          "upvotes": 4,
          "replies": {}
        }
      }
    },
    "h00o00o": {
      "link": "/r/college/comments/nolbfy/graduation/h00o00o/",
      "text": "Congrats!",
      "author": "CityLightsWriter",
      "created": 1622411778,
      "upvotes": 19,
      "replies": {
        "h02cmh9": {
          "link": "/r/college/comments/nolbfy/graduation/h02cmh9/",
          "text": "Thank youu",
          "author": "HamedR6S",
          "created": 1622451994,
          "upvotes": 5,
          "replies": {}
        }
      }
    },
    "h00mrdi": {
      "link": "/r/college/comments/nolbfy/graduation/h00mrdi/",
      "text": "Congratsss u made it. Welcome to the real world",
      "author": "kickme29944",
      "created": 1622411146,
      "upvotes": 62,
      "replies": {
        "h02cm5g": {
          "link": "/r/college/comments/nolbfy/graduation/h02cm5g/",
          "text": "Thank you, can't wait to see what the real world has to offer!",
          "author": "HamedR6S",
          "created": 1622451985,
          "upvotes": 23,
          "replies": {
            "h02m2kh": {
              "link": "/r/college/comments/nolbfy/graduation/h02m2kh/",
              "text": "Disappointment and despair awaits. Jk congrats on graduating!",
              "author": "danishcornhen",
              "created": 1622460789,
              "upvotes": 21,
              "replies": {
                "h02m6w4": {
                  "link": "/r/college/comments/nolbfy/graduation/h02m6w4/",
                  "text": "Ouchy thank you!",
                  "author": "HamedR6S",
                  "created": 1622460890,
                  "upvotes": 7,
                  "replies": {}
                },
                "h1t3l8o": {
                  "link": "/r/college/comments/nolbfy/graduation/h1t3l8o/",
                  "text": "But it is the truth",
                  "author": "nalinpuri",
                  "created": 1623726360,
                  "upvotes": 1,
                  "replies": {}
                }
              }
            }
          }
        }
      }
    }
  },
  "updated": 1634055977
}