{
  "sid": "rgenqi",
  "link": "/r/college/comments/rgenqi/please_wish_me_luck/",
  "title:": "Please wish me luck! \ud83c\udf40",
  "text": "I have my last final exam at 2:15 and I\u2019m kinda nervous. Please wish me luck I\u2019m going to need it \ud83d\ude05\n\nEdit: thank you everyone for the support! I passed the exam with 92% \ud83e\udd29\ud83e\udd73 I passed the class",
  "author": "ShyCoconut0_0",
  "created": 1639508709,
  "updated": 1639861008,
  "over_18": false,
  "upvotes": 19,
  "upvote_ratio": 1.0,
  "comments": {
    "hojnug8": {
      "link": "/r/college/comments/rgenqi/please_wish_me_luck/hojnug8/",
      "text": "good luck",
      "author": "winkdinkdoo",
      "created": 1639508762,
      "upvotes": 1,
      "replies": {}
    },
    "hojq57w": {
      "link": "/r/college/comments/rgenqi/please_wish_me_luck/hojq57w/",
      "text": "\ud83c\udf40\ud83c\udf40",
      "author": "queendabliss",
      "created": 1639509665,
      "upvotes": 1,
      "replies": {}
    },
    "hojqsmo": {
      "link": "/r/college/comments/rgenqi/please_wish_me_luck/hojqsmo/",
      "text": "U got this bestie \ud83c\udf40\ud83c\udf40\ud83c\udf40",
      "author": "Deepseadyson",
      "created": 1639509919,
      "upvotes": 1,
      "replies": {}
    },
    "hojriq6": {
      "link": "/r/college/comments/rgenqi/please_wish_me_luck/hojriq6/",
      "text": "All the best",
      "author": "consultingedge",
      "created": 1639510200,
      "upvotes": 1,
      "replies": {}
    },
    "hojvc8c": {
      "link": "/r/college/comments/rgenqi/please_wish_me_luck/hojvc8c/",
      "text": "All the best!",
      "author": "clichelover_22",
      "created": 1639511690,
      "upvotes": 1,
      "replies": {}
    },
    "hok2wfd": {
      "link": "/r/college/comments/rgenqi/please_wish_me_luck/hok2wfd/",
      "text": "Best of luck \ud83d\udc4d",
      "author": "SuddenVermicelli7820",
      "created": 1639514662,
      "upvotes": 1,
      "replies": {}
    },
    "hok4rnf": {
      "link": "/r/college/comments/rgenqi/please_wish_me_luck/hok4rnf/",
      "text": "you got this man, not sure if you\u2019re done it already but I\u2019m sure you aced it",
      "author": "Leidl_",
      "created": 1639515422,
      "upvotes": 1,
      "replies": {}
    },
    "hokq6zv": {
      "link": "/r/college/comments/rgenqi/please_wish_me_luck/hokq6zv/",
      "text": "Hey, congrats",
      "author": "EconomyMountain2827",
      "created": 1639524404,
      "upvotes": 1,
      "replies": {}
    },
    "hokq9zw": {
      "link": "/r/college/comments/rgenqi/please_wish_me_luck/hokq9zw/",
      "text": "Yes!! Let's goooooo :) Congrats! :)",
      "author": "designingwoman",
      "created": 1639524441,
      "upvotes": 1,
      "replies": {}
    },
    "hon5blq": {
      "link": "/r/college/comments/rgenqi/please_wish_me_luck/hon5blq/",
      "text": "Break a pen!",
      "author": "ThroawayPartyer",
      "created": 1639575617,
      "upvotes": 1,
      "replies": {}
    }
  }
}