{
  "sid": "qq2t78",
  "link": "/r/ApplyingToCollege/comments/qq2t78/please_help_me/",
  "title:": "Please Help me !!!",
  "text": "**Hi Everyone So diving into my problem, I have a low SAT score of 1270 and I am wondering of I can apply to any University and would that accept me. I am an International Student. Are there any other ways to impress the universities like any activities or skills? I am in my 11th grade btw and ready to invest some time.** \n\n&#x200B;\n\n**PLEASE HELP ME**",
  "author": "MOHITRAJ32",
  "created": 1636461601,
  "updated": 1636653529,
  "over_18": false,
  "upvotes": 0,
  "upvote_ratio": 0.5,
  "comments": {
    "hjxi5x5": {
      "link": "/r/ApplyingToCollege/comments/qq2t78/please_help_me/hjxi5x5/",
      "text": "If you're still in 11th grade, you can always retake the test for a higher score, or even go test optional when you apply next year.",
      "author": "prsehgal",
      "created": 1636462658,
      "upvotes": 5,
      "replies": {}
    },
    "hjxk2nb": {
      "link": "/r/ApplyingToCollege/comments/qq2t78/please_help_me/hjxk2nb/",
      "text": "If you can pay full price, yes.  There are many universities where a 1270 would place you in the top half of enrolled students.",
      "author": "jayphoward",
      "created": 1636463723,
      "upvotes": 2,
      "replies": {}
    },
    "hjxhcgk": {
      "link": "/r/ApplyingToCollege/comments/qq2t78/please_help_me/hjxhcgk/",
      "text": "There are lots of good universities that would accept you. For eg. IUPUI, Georgia State, Penn State, Michigan State etc",
      "author": "Arnavsmayan",
      "created": 1636462190,
      "upvotes": 1,
      "replies": {}
    }
  }
}