{
  "sid": "qxgfkj",
  "link": "/r/ApplyingToCollege/comments/qxgfkj/utampa_acceptanceinternational/",
  "title:": "UTampa acceptance/International",
  "text": "Wait what.. I didn\u2019t receive an email but I just logged into all of my college portals to check I didn\u2019t have any documents missing and I saw a Congratulations message in the University of Tampa portal\ud83d\ude2d\u2764\ufe0f I thought the admissions decisions would come in 20th of December but I guess not. I\u2019m so excited I tought that it would be impossible to get into anywhere as an international but hey I\u2019m going to college next year\ud83e\udd73",
  "author": "Calm_Review1943",
  "created": 1637329262,
  "updated": 1637365673,
  "over_18": false,
  "upvotes": 8,
  "upvote_ratio": 1.0,
  "comments": {
    "hla6uzw": {
      "link": "/r/ApplyingToCollege/comments/qxgfkj/utampa_acceptanceinternational/hla6uzw/",
      "text": "Congrats!\n\nIs it affordable?",
      "author": "elkrange",
      "created": 1637345216,
      "upvotes": 3,
      "replies": {}
    },
    "hla02ls": {
      "link": "/r/ApplyingToCollege/comments/qxgfkj/utampa_acceptanceinternational/hla02ls/",
      "text": "Yayyyy!!! Congratulations!!",
      "author": "Megaboy_19",
      "created": 1637342572,
      "upvotes": 0,
      "replies": {}
    },
    "hlauiru": {
      "link": "/r/ApplyingToCollege/comments/qxgfkj/utampa_acceptanceinternational/hlauiru/",
      "text": "Ayeeeee I got in too! Congrats",
      "author": "shekyy_lopie",
      "created": 1637354022,
      "upvotes": 1,
      "replies": {}
    }
  }
}