{
  "sid": "qv0elm",
  "link": "/r/ApplyingToCollege/comments/qv0elm/school_has_made_my_mental_health_so_much_better/",
  "title:": "school has made my mental health so much better",
  "text": "it's actually crazy, thought i was gonna not like going back to in person pe but heyyy at least i can talk to friends\n\nsadly as seniors all we talk abt is college apps but its fineee",
  "author": "AggravatingNail7400",
  "created": 1637040267,
  "updated": 1637179575,
  "over_18": false,
  "upvotes": 3,
  "upvote_ratio": 1.0,
  "comments": {
    "hkuzvz7": {
      "link": "/r/ApplyingToCollege/comments/qv0elm/school_has_made_my_mental_health_so_much_better/hkuzvz7/",
      "text": "I think you aren\u2019t alone there. One of my students actually wrote an essay about how the pandemic made her appreciate school in a way she never had before",
      "author": "admissionsmom",
      "created": 1637075426,
      "upvotes": 1,
      "replies": {}
    }
  }
}