{
  "sid": "revwpi",
  "link": "/r/ApplyingToCollege/comments/revwpi/rolling_admissions/",
  "title:": "Rolling Admissions",
  "text": "How long does it take for rolling admission decisions to come? \n\nI applied to Florida Tech in the beginning of November, same time as EAs, but still haven\u2019t gotten a decision. Some websites say it takes up to 2 weeks, others say 4-6 weeks, some even say 6-8. So I\u2019m not sure if there\u2019s been some issue with my application.",
  "author": "GoatZizGoat25",
  "created": 1639336305,
  "updated": 1639514823,
  "over_18": false,
  "upvotes": 2,
  "upvote_ratio": 1.0,
  "comments": {
    "hoaag78": {
      "link": "/r/ApplyingToCollege/comments/revwpi/rolling_admissions/hoaag78/",
      "text": "[deleted]",
      "author": null,
      "created": 1639338166,
      "upvotes": 2,
      "replies": {
        "hoas4f8": {
          "link": "/r/ApplyingToCollege/comments/revwpi/rolling_admissions/hoas4f8/",
          "text": "I applied on Nov 1st. There were no essays and I am international but I\u2019m not asking for aid. I\u2019m guessing there\u2019s a lot of applications since I applied around the same time as most EA deadlines are.",
          "author": "GoatZizGoat25",
          "created": 1639345261,
          "upvotes": 1,
          "replies": {}
        }
      }
    },
    "hoaav3m": {
      "link": "/r/ApplyingToCollege/comments/revwpi/rolling_admissions/hoaav3m/",
      "text": "Check your portal.  I got one within the two week time span and I got another after like a month.  \n\nThe beauty of it for the school is that they can send it out whenever they want (and you can send it in whenever you want, so it\u2019s a win-win).",
      "author": "SupermarketWild3834",
      "created": 1639338330,
      "upvotes": 2,
      "replies": {
        "hoarund": {
          "link": "/r/ApplyingToCollege/comments/revwpi/rolling_admissions/hoarund/",
          "text": "Checked my portal, no decision. Just has a thank you page and a checklist (all checked). I\u2019m international but I\u2019m not asking for aid so not sure why it\u2019s taking nearly 6 weeks.",
          "author": "GoatZizGoat25",
          "created": 1639345153,
          "upvotes": 1,
          "replies": {}
        }
      }
    }
  }
}