{
  "sid": "qitbca",
  "link": "/r/ApplyingToCollege/comments/qitbca/anybody_willing_to_read_my_uchicago_quirky_essay/",
  "title:": "Anybody willing to read my UChicago Quirky essay?",
  "text": "Title.",
  "author": "Aware-Eggplant",
  "created": 1635565720,
  "updated": 1635779174,
  "over_18": false,
  "upvotes": 3,
  "upvote_ratio": 0.72,
  "comments": {
    "hilpvhb": {
      "link": "/r/ApplyingToCollege/comments/qitbca/anybody_willing_to_read_my_uchicago_quirky_essay/hilpvhb/",
      "text": "I\u2019m happy to (full disclosure I\u2019m also a senior so if u don\u2019t want me to read it I understand)- but be careful sending essays on the internet",
      "author": "Alternative_Gene_655",
      "created": 1635565954,
      "upvotes": 9,
      "replies": {}
    },
    "himcpc1": {
      "link": "/r/ApplyingToCollege/comments/qitbca/anybody_willing_to_read_my_uchicago_quirky_essay/himcpc1/",
      "text": "Stop sending ur essays to seniors who are also applying",
      "author": "ConfidentMangoApple",
      "created": 1635582068,
      "upvotes": 4,
      "replies": {}
    },
    "hilvdtq": {
      "link": "/r/ApplyingToCollege/comments/qitbca/anybody_willing_to_read_my_uchicago_quirky_essay/hilvdtq/",
      "text": "Sure, I\u2019m not applying to UChicago and honestly wanna see what y\u2019all are doing for those lol",
      "author": "pieceof_pie",
      "created": 1635569199,
      "upvotes": 3,
      "replies": {}
    },
    "hilpvas": {
      "link": "/r/ApplyingToCollege/comments/qitbca/anybody_willing_to_read_my_uchicago_quirky_essay/hilpvas/",
      "text": "I'm not applying to Hicago, I can review it if you want",
      "author": "a2c2021throwaway",
      "created": 1635565952,
      "upvotes": 2,
      "replies": {
        "hilu6n5": {
          "link": "/r/ApplyingToCollege/comments/qitbca/anybody_willing_to_read_my_uchicago_quirky_essay/hilu6n5/",
          "text": "Same here, PMs open",
          "author": "CardMechanica",
          "created": 1635568464,
          "upvotes": 2,
          "replies": {}
        }
      }
    },
    "hilxm1r": {
      "link": "/r/ApplyingToCollege/comments/qitbca/anybody_willing_to_read_my_uchicago_quirky_essay/hilxm1r/",
      "text": "also have my quirky essay done.  gl, hopefully future classmates?",
      "author": "chuuuuuu-",
      "created": 1635570630,
      "upvotes": 2,
      "replies": {
        "hilxx93": {
          "link": "/r/ApplyingToCollege/comments/qitbca/anybody_willing_to_read_my_uchicago_quirky_essay/hilxx93/",
          "text": "Yesssss. Good luck bestie!",
          "author": "Aware-Eggplant",
          "created": 1635570843,
          "upvotes": 1,
          "replies": {}
        }
      }
    },
    "him1jmu": {
      "link": "/r/ApplyingToCollege/comments/qitbca/anybody_willing_to_read_my_uchicago_quirky_essay/him1jmu/",
      "text": "i\u2019m not applying to uchicago so you can send it to me!!",
      "author": "Due-Pace-3305",
      "created": 1635573367,
      "upvotes": 2,
      "replies": {}
    },
    "him2282": {
      "link": "/r/ApplyingToCollege/comments/qitbca/anybody_willing_to_read_my_uchicago_quirky_essay/him2282/",
      "text": "You can send it to me. Thanks.",
      "author": "Soft-Course-5234",
      "created": 1635573746,
      "upvotes": 2,
      "replies": {}
    },
    "him74tk": {
      "link": "/r/ApplyingToCollege/comments/qitbca/anybody_willing_to_read_my_uchicago_quirky_essay/him74tk/",
      "text": "Im not applying to uchicago so u can send it to me if u want",
      "author": "No_Parfait_7051",
      "created": 1635577574,
      "upvotes": 2,
      "replies": {}
    },
    "hiqogs6": {
      "link": "/r/ApplyingToCollege/comments/qitbca/anybody_willing_to_read_my_uchicago_quirky_essay/hiqogs6/",
      "text": "Yo I just submitted my application too!  (Did the pie one)  would love to go over yours if you want that",
      "author": "NiftySpigots",
      "created": 1635666214,
      "upvotes": 2,
      "replies": {}
    },
    "hime86s": {
      "link": "/r/ApplyingToCollege/comments/qitbca/anybody_willing_to_read_my_uchicago_quirky_essay/hime86s/",
      "text": "I'd like to read it!!",
      "author": "Jkrocks47",
      "created": 1635583336,
      "upvotes": 1,
      "replies": {}
    }
  }
}