{
  "sid": "r2f2f9",
  "link": "/r/ApplyingToCollege/comments/r2f2f9/stem_student_here_i_am_going_to_take_the_sat_in_8/",
  "title:": "STEM Student here. I am going to take the SAT in 8 days and I just realized that the ACT is better for STEM Students. Am I screwed?",
  "text": "As it says in title  \n\n\nhelp",
  "author": "Aadgoat101",
  "created": 1637901962,
  "updated": 1638206222,
  "over_18": false,
  "upvotes": 0,
  "upvote_ratio": 0.4,
  "comments": {
    "hm4jotn": {
      "link": "/r/ApplyingToCollege/comments/r2f2f9/stem_student_here_i_am_going_to_take_the_sat_in_8/hm4jotn/",
      "text": "Neither test is necessarily \"better\" for a particular kind of student... Take the SAT since you're already signed up for it, and then take an ACT diagnostic test to see if it works for you.",
      "author": "prsehgal",
      "created": 1637906829,
      "upvotes": 11,
      "replies": {
        "hm4kxck": {
          "link": "/r/ApplyingToCollege/comments/r2f2f9/stem_student_here_i_am_going_to_take_the_sat_in_8/hm4kxck/",
          "text": "I see, if I am able to score really good on the ACT, why not take it? I understand",
          "author": "Aadgoat101",
          "created": 1637907648,
          "upvotes": 2,
          "replies": {}
        }
      }
    },
    "hm4kjyz": {
      "link": "/r/ApplyingToCollege/comments/r2f2f9/stem_student_here_i_am_going_to_take_the_sat_in_8/hm4kjyz/",
      "text": "You're fine. I took the SAT and I'm a STEM student. Plenty of people I know are STEM students and took the SAT. We all did fine. \n\nYou can take an ACT diagnostic to see if you score better, and if you do, it might be worth taking.",
      "author": "dominaxe",
      "created": 1637907405,
      "upvotes": 5,
      "replies": {
        "hm4ksbu": {
          "link": "/r/ApplyingToCollege/comments/r2f2f9/stem_student_here_i_am_going_to_take_the_sat_in_8/hm4ksbu/",
          "text": "I already score close to a perfect on the SAT and I studied hard to get there. I really don\u2019t wanna put in the same effort for the ACT if i don\u2019t have to but if it helps my admissions chances I shall.",
          "author": "Aadgoat101",
          "created": 1637907558,
          "upvotes": -2,
          "replies": {
            "hm4llas": {
              "link": "/r/ApplyingToCollege/comments/r2f2f9/stem_student_here_i_am_going_to_take_the_sat_in_8/hm4llas/",
              "text": "Oh that's wonderful then! You don't need to take the ACT if you're already scoring great on the SAT. Once you get a great score, focus on the rest of your application.",
              "author": "dominaxe",
              "created": 1637908105,
              "upvotes": 4,
              "replies": {
                "hm4pysm": {
                  "link": "/r/ApplyingToCollege/comments/r2f2f9/stem_student_here_i_am_going_to_take_the_sat_in_8/hm4pysm/",
                  "text": "Yeah, but I worry if the college interviewer asks me why I chose the sat over the act\u2026",
                  "author": "Aadgoat101",
                  "created": 1637911222,
                  "upvotes": -1,
                  "replies": {
                    "hm4rxcp": {
                      "link": "/r/ApplyingToCollege/comments/r2f2f9/stem_student_here_i_am_going_to_take_the_sat_in_8/hm4rxcp/",
                      "text": "I promise you, nobody's going to ask you that. So many STEM students get in wonderful schools with SAT instead of the ACT.",
                      "author": "dominaxe",
                      "created": 1637912696,
                      "upvotes": 5,
                      "replies": {
                        "hm4saf8": {
                          "link": "/r/ApplyingToCollege/comments/r2f2f9/stem_student_here_i_am_going_to_take_the_sat_in_8/hm4saf8/",
                          "text": "Sweet relief",
                          "author": "Aadgoat101",
                          "created": 1637912970,
                          "upvotes": -1,
                          "replies": {}
                        }
                      }
                    }
                  }
                }
              }
            }
          }
        }
      }
    },
    "hm4koxe": {
      "link": "/r/ApplyingToCollege/comments/r2f2f9/stem_student_here_i_am_going_to_take_the_sat_in_8/hm4koxe/",
      "text": "What makes you think that \"ACT is better for STEM Students.\"???",
      "author": "RichInPitt",
      "created": 1637907496,
      "upvotes": 3,
      "replies": {
        "hm4ktau": {
          "link": "/r/ApplyingToCollege/comments/r2f2f9/stem_student_here_i_am_going_to_take_the_sat_in_8/hm4ktau/",
          "text": "it really is",
          "author": "SarimROTI",
          "created": 1637907575,
          "upvotes": 1,
          "replies": {}
        },
        "hm4ku0g": {
          "link": "/r/ApplyingToCollege/comments/r2f2f9/stem_student_here_i_am_going_to_take_the_sat_in_8/hm4ku0g/",
          "text": "Has a science section",
          "author": "Aadgoat101",
          "created": 1637907588,
          "upvotes": 1,
          "replies": {
            "hm4l0vt": {
              "link": "/r/ApplyingToCollege/comments/r2f2f9/stem_student_here_i_am_going_to_take_the_sat_in_8/hm4l0vt/",
              "text": "The Science section is more of a data interpretation section which is already sprinkled around different parts of the SAT.",
              "author": "prsehgal",
              "created": 1637907714,
              "upvotes": 11,
              "replies": {
                "hm4pzrv": {
                  "link": "/r/ApplyingToCollege/comments/r2f2f9/stem_student_here_i_am_going_to_take_the_sat_in_8/hm4pzrv/",
                  "text": "Oh that\u2019s relieving",
                  "author": "Aadgoat101",
                  "created": 1637911242,
                  "upvotes": 1,
                  "replies": {}
                }
              }
            }
          }
        },
        "hm58ojt": {
          "link": "/r/ApplyingToCollege/comments/r2f2f9/stem_student_here_i_am_going_to_take_the_sat_in_8/hm58ojt/",
          "text": "It shouldn't be but for some reason a few universities abroad weigh the ACT more than the SAT. E.g. for a certain scholarship in the University of Melbourne, you need to have either a 1500+ SAT or a 31+ ACT. 31 is roughly 1390-1410.\n\nDefos not the case for US colleges though",
          "author": "9und9zigluftwaffles",
          "created": 1637926792,
          "upvotes": 1,
          "replies": {
            "hm5pfbg": {
              "link": "/r/ApplyingToCollege/comments/r2f2f9/stem_student_here_i_am_going_to_take_the_sat_in_8/hm5pfbg/",
              "text": "Wouldn\u2019t that meant the SAT is viewed more highly? That would indicate that a higher SAT score is equivalent to a lower ACT.",
              "author": "TakeTheWs",
              "created": 1637937595,
              "upvotes": 1,
              "replies": {
                "hm6qcpj": {
                  "link": "/r/ApplyingToCollege/comments/r2f2f9/stem_student_here_i_am_going_to_take_the_sat_in_8/hm6qcpj/",
                  "text": "No? I mean they're essentially lowering the bar for ACT and higher for SAT. They view the ACT more highly as a lower ACT score is seen to be equivalent to a higher SAT score.",
                  "author": "9und9zigluftwaffles",
                  "created": 1637954480,
                  "upvotes": 2,
                  "replies": {}
                }
              }
            }
          }
        }
      }
    },
    "hm4k0rf": {
      "link": "/r/ApplyingToCollege/comments/r2f2f9/stem_student_here_i_am_going_to_take_the_sat_in_8/hm4k0rf/",
      "text": "If you are a good enough test taker you can do well on either test.",
      "author": "AuthenticPhantom",
      "created": 1637907046,
      "upvotes": 2,
      "replies": {}
    },
    "hm4tw15": {
      "link": "/r/ApplyingToCollege/comments/r2f2f9/stem_student_here_i_am_going_to_take_the_sat_in_8/hm4tw15/",
      "text": "I'm a STEM student. I got a good score on SAT. Definitely not something to waste your time worrying about.",
      "author": "Concerned-gay-guy",
      "created": 1637914180,
      "upvotes": 1,
      "replies": {}
    }
  }
}